slash3/VERSION
slash3/__init__.py
slash3/key.py
slash3/logging.py
slash3/py.typed
slash3/uri.py
slash3-1.1.1.dist-info/LICENSE
slash3-1.1.1.dist-info/METADATA
slash3-1.1.1.dist-info/WHEEL
slash3-1.1.1.dist-info/top_level.txt
slash3-1.1.1.dist-info/RECORD
