Metadata-Version: 2.1
Name: slash3
Version: 1.1.1
Summary: Builds and navigates Amazon Web Services S3 URIs
Author: Cariad Eccleston
Author-email: cariad@cariad.earth
License: MIT
Project-URL: Documentation, https://cariad.github.io/slash3/slash3.html
Project-URL: Source, https://github.com/cariad/slash3
Classifier: Development Status :: 5 - Production/Stable
Classifier: License :: OSI Approved :: MIT License
Classifier: Natural Language :: English
Classifier: Operating System :: OS Independent
Classifier: Programming Language :: Python :: 3 :: Only
Classifier: Programming Language :: Python :: 3.10
Classifier: Programming Language :: Python :: 3.11
Classifier: Programming Language :: Python :: 3.9
Classifier: Typing :: Typed
Requires-Python: >=3.9
License-File: LICENSE
